jupyter_tree_download/__init__.py
jupyter_tree_download/handlers.py
jupyter_tree_download/etc/nbconfig/jupyter-tree-download.json
jupyter_tree_download/etc/serverextension/jupyter-tree-download.json
jupyter_tree_download/static/tree.js
jupyter_tree_download-1.0.1.data/data/etc/jupyter/jupyter_notebook_config.d/jupyter-tree-download.json
jupyter_tree_download-1.0.1.data/data/etc/jupyter/nbconfig/tree.d/jupyter-tree-download.json
jupyter_tree_download-1.0.1.data/data/share/jupyter/nbextensions/jupyter_tree_download/tree.js
jupyter_tree_download-1.0.1.dist-info/LICENSE
jupyter_tree_download-1.0.1.dist-info/METADATA
jupyter_tree_download-1.0.1.dist-info/WHEEL
jupyter_tree_download-1.0.1.dist-info/top_level.txt
jupyter_tree_download-1.0.1.dist-info/RECORD
